pickle_com/__init__.py
pickle_com-0.1.0.dist-info/METADATA
pickle_com-0.1.0.dist-info/WHEEL
pickle_com-0.1.0.dist-info/top_level.txt
pickle_com-0.1.0.dist-info/RECORD
