Metadata-Version: 2.4
Name: pickle_com
Version: 0.1.0
Summary: A drop-in pickle replacement compatible with legacy numpy attributes and inspect.getargspec.
Author-email: Yu Sun <yusunhit@gmail.com>
License: MIT
Requires-Python: >=3.7
Requires-Dist: numpy
